ppg_features/__init__.py
ppg_features/ppg_features.py
ppg_features-1.3.1.data/scripts/ppg_features.py
ppg_features-1.3.1.dist-info/METADATA
ppg_features-1.3.1.dist-info/RECORD
ppg_features-1.3.1.dist-info/WHEEL
ppg_features-1.3.1.dist-info/top_level.txt
